<?xml version="1.0" encoding="utf-8" ?>
<Defs>

	<JoyGiverDef>
		<defName>STE_Study_DummyTable</defName>
		<giverClass>JoyGiver_WatchBuilding</giverClass>
		<baseChance>2</baseChance>
		<thingDefs>
			<li>STE_DummyTable</li>
		</thingDefs>
		<jobDef>STE_Study_Medicine</jobDef>
		<desireSit>false</desireSit>
		<joyKind>STE_Study_Medicine</joyKind>
		<requiredCapacities>
			<li>Manipulation</li>
		</requiredCapacities>
	</JoyGiverDef>

	<JoyGiverDef>
		<defName>STE_Study_Melee</defName>
		<giverClass>JoyGiver_WatchBuilding</giverClass>
		<baseChance>2</baseChance>
		<thingDefs>
			<li>STE_PunchingBag</li>
			<li>STE_KickingTarget</li>
		</thingDefs>
		<jobDef>STE_Study_Melee</jobDef>
		<desireSit>false</desireSit>
		<joyKind>STE_Study_Melee</joyKind>
		<requiredCapacities>
			<li>Manipulation</li>
		</requiredCapacities>
	</JoyGiverDef>

	<JoyGiverDef>
		<defName>STE_Study_Shooting</defName>
		<giverClass>JoyGiver_WatchBuilding</giverClass>
		<baseChance>2</baseChance>
		<thingDefs>
			<li>STE_ShootingTarget</li>
			<li>STE_ShootingDummy</li>
		</thingDefs>
		<jobDef>STE_Study_Shooting</jobDef>
		<desireSit>false</desireSit>
		<joyKind>STE_Study_Shooting</joyKind>
		<requiredCapacities>
			<li>Manipulation</li>
		</requiredCapacities>
	</JoyGiverDef>
  
</Defs>